{
  "help": {
    "permissionDefinition": {
      "code": "مفتاح فريد يستخدمه حراس المسار والصفحة.",
      "name": "الاسم المعروض للمسؤولين عند إدارة الأذونات.",
      "description": "شرح داخلي اختياري لهذا الإذن.",
      "isActive": "الأذونات غير النشطة لا تؤخذ بعين الاعتبار عند حساب وصول المستخدم.",
      "save": "التغييرات تؤثر على تدفقات تفويض الأدوار والمجموعات."
    },
    "permissionGroup": {
      "name": "اسم المجموعة للتعريف عند التعيين للمستخدمين.",
      "isSystemAdmin": "يمكن لأعضاء هذه المجموعة الوصول إلى جميع الصفحات والإجراءات دون فحوصات فردية.",
      "isActive": "لا ينبغي تعيين المجموعات غير النشطة لقرارات الوصول الجديدة.",
      "permissions": "الأذونات المحددة تحدد ما يمكن لأعضاء المجموعة الوصول إليه.",
      "save": "يحدث الوصول الفعلي لجميع المستخدمين المعينين لهذه المجموعة."
    },
    "userAssignment": {
      "user": "اختر المستخدم الذي تريد إدارة نطاق وصوله.",
      "groups": "يتلقى المستخدم أذونات مدمجة من جميع المجموعات المحددة.",
      "save": "تُطبق التعيينات فوراً. قد يحتاج المستخدمون إلى تحديث جلستهم.",
      "systemAdminNote": "إذا كان للمستخدم مجموعة مسؤول النظام، يتم تجاوز الأذونات التفصيلية."
    },
    "wmsScopePolicy": {
      "code": "Policy code is the stable key used by backend enforcement and support flows.",
      "name": "Operational display name that explains why the policy exists.",
      "entityType": "Determines which document or workflow type this policy applies to.",
      "scopeType": "Defines whether access is unrestricted, branch-based, warehouse-based, or assigned-only.",
      "description": "Optional internal note used for support and audit context."
    }
  },
  "permissionDefinitions": {
    "title": "تعريفات الأذونات",
    "description": "إدارة رموز الأذونات المستخدمة في النظام",
    "add": "إضافة تعريف",
    "form": {
      "editTitle": "تعديل تعريف الصلاحية",
      "addTitle": "إضافة تعريف صلاحية",
      "editDescription": "تحديث بيانات تعريف الصلاحية",
      "addDescription": "إنشاء تعريف صلاحية جديد",
      "code": "الرمز",
      "codePlaceholder": "اختر رمزاً",
      "affectedRoutes": "الصفحات المتأثرة",
      "affectedRoutesNone": "لا يوجد مسار مطابق لهذا الرمز",
      "name": "الاسم",
      "namePlaceholder": "الاسم الظاهر",
      "description": "الوصف",
      "descriptionPlaceholder": "وصف اختياري",
      "isActive": "نشط",
      "codeSearchPlaceholder": "بحث...",
      "codeEmpty": "لا توجد نتائج"
    },
    "table": {
      "code": "الرمز",
      "name": "الاسم",
      "isActive": "نشط",
      "updatedDate": "تاريخ التحديث",
      "showing": "{{from}}-{{to}} / {{total}}"
    },
    "delete": {
      "confirmTitle": "حذف تعريف الصلاحية",
      "confirmMessage": "هل تريد بالتأكيد حذف «{{name}}»؟ لا يمكن التراجع عن هذا الإجراء."
    },
    "syncFromRoutes": "مزامنة من المسارات"
  },
  "permissionGroups": {
    "title": "مجموعات الأذونات",
    "description": "إدارة مجموعات الأذونات وتعييناتها",
    "add": "إضافة مجموعة",
    "selectAll": "تحديد الكل",
    "noDefinitions": "لا تتوفر تعريفات أذونات",
    "form": {
      "editTitle": "تعديل مجموعة الصلاحيات",
      "addTitle": "إضافة مجموعة صلاحيات",
      "editDescription": "تحديث بيانات المجموعة",
      "addDescription": "إنشاء مجموعة صلاحيات جديدة",
      "name": "الاسم",
      "namePlaceholder": "اسم المجموعة",
      "description": "الوصف",
      "descriptionPlaceholder": "وصف اختياري",
      "isSystemAdmin": "مسؤول النظام",
      "isActive": "نشط",
      "permissions": "الصلاحيات"
    },
    "table": {
      "name": "الاسم",
      "isSystemAdmin": "مسؤول النظام",
      "isActive": "نشط",
      "permissionCount": "الصلاحيات",
      "showing": "{{from}}-{{to}} / {{total}}"
    },
    "managePermissions": "إدارة الأذونات",
    "permissionsPanel": {
      "title": "تعديل صلاحيات المجموعة",
      "description": "حدد الصلاحيات لهذه المجموعة",
      "currentCodes": "رموز الصلاحيات الحالية",
      "introTitle": "What can this group do?",
      "introBody": "Below, you choose which modules this group can view, create, update, or delete. Every user assigned to this group receives the same permission set.",
      "selectionSummaryTitle": "Selected CRUD summary",
      "selectionSummaryBody": "This summary helps you quickly see which operation types are currently granted to the group.",
      "searchPlaceholder": "Search by module, action, or permission name...",
      "selectActionGroup": "Select all {{action}} permissions"
    },
    "delete": {
      "confirmTitle": "حذف مجموعة الصلاحيات",
      "confirmMessage": "هل تريد بالتأكيد حذف «{{name}}»؟ لا يمكن التراجع عن هذا الإجراء."
    },
    "search": "بحث...",
    "systemAdminLocked": "لا يمكن تعديل مجموعة مسؤول النظام"
  },
  "userGroupAssignments": {
    "title": "تعيينات مجموعات المستخدمين",
    "description": "تعيين مجموعات الأذونات للمستخدمين",
    "selectUser": "اختر مستخدماً",
    "selectUserPlaceholder": "ابحث وحدد مستخدماً...",
    "selectUserHint": "حدد مستخدماً لإدارة تعيينات مجموعاته",
    "assignedGroups": "مجموعات الأذونات المعينة",
    "noUsers": "لم يتم العثور على مستخدمين",
    "noGroups": "لا تتوفر مجموعات أذونات",
    "selectAll": "تحديد الكل"
  },
  "common": {
    "cancel": "إلغاء",
    "saving": "جارٍ الحفظ...",
    "save": "حفظ وتطبيق",
    "loading": "جارٍ التحميل...",
    "search": "بحث...",
    "noData": "لا توجد بيانات",
    "actions": "إجراءات",
    "yes": "نعم",
    "no": "لا",
    "edit": "تعديل",
    "delete": "حذف",
    "previous": "السابق",
    "next": "التالي",
    "processing": "جارٍ المعالجة..."
  },
  "sidebar": {
    "accessControl": "التحكم في الوصول",
    "permissionDefinitions": "تعريفات الأذونات",
    "permissionGroups": "مجموعات الأذونات",
    "userGroupAssignments": "تعيينات مجموعات المستخدمين",
    "wmsScopePolicies": "B2B Scope Policies",
    "wmsScopeAssignments": "B2B Scope Assignments"
  },
  "accessControl": {
    "permissionActions": {
      "view": {
        "description": "Opens list, detail, and read-only monitoring screens."
      },
      "create": {
        "description": "Opens new record creation and first-save steps."
      },
      "update": {
        "description": "Opens edit, process, and change-saving steps for existing records."
      },
      "delete": {
        "description": "Allows soft delete, deactivation, or delete actions."
      }
    }
  },
  "wmsScopePolicies": {
    "title": "B2B Scope Policies",
    "description": "Manage branch, customer, catalog, and assignment-based data scope rules",
    "add": "Add Policy",
    "stats": {
      "total": "Total Policies",
      "active": "Active Policies",
      "entities": "Covered Flows"
    },
    "form": {
      "addTitle": "Add B2B Scope Policy",
      "editTitle": "Edit B2B Scope Policy",
      "addDescription": "Define a new data-scope policy.",
      "editDescription": "Update the policy behavior and scope type.",
      "code": "Code",
      "codePlaceholder": "Select a policy code",
      "codeEmpty": "No suitable policy code found",
      "name": "Name",
      "namePlaceholder": "Policy display name",
      "entityType": "Entity Type",
      "entityTypePlaceholder": "Select an entity type",
      "scopeType": "Scope Type",
      "scopeTypePlaceholder": "Select a scope type",
      "description": "Description",
      "descriptionPlaceholder": "Explain the operational context",
      "includeSelf": "Include Own Records",
      "includeSelfHint": "Allows the user to also see their own records when the policy is assignment, branch, or warehouse based.",
      "isActive": "Active",
      "isActiveHint": "Inactive policies are ignored in resolution and assignment flows."
    },
    "table": {
      "code": "Code",
      "name": "Name",
      "entityType": "Entity Type",
      "scopeType": "Scope Type",
      "includeSelf": "Include Self",
      "isActive": "Active"
    },
    "delete": {
      "confirmTitle": "Delete B2B Scope Policy",
      "confirmMessage": "Are you sure you want to delete \"{{name}}\"?"
    }
  },
  "wmsScopeAssignments": {
    "title": "B2B Scope Assignments",
    "description": "Manage which branch, customer, catalog, and record scope each user can operate on",
    "selectUser": "Select User",
    "selectUserPlaceholder": "Search and select user...",
    "selectUserHint": "Choose a user to edit scope assignments.",
    "noUserSelected": "No user selected yet",
    "noUsers": "No users found",
    "assignedPolicies": "Assigned Policies",
    "resolutionScope": "Reviewed Flow",
    "statusLabel": "Status",
    "statusPending": "Unsaved changes",
    "statusCurrent": "In sync with server",
    "editorTitle": "Assignment Editor",
    "editorDescription": "You can define branch and warehouse based scope for multiple entity types.",
    "addAssignment": "Add Assignment",
    "empty": "This user does not have any B2B scope assignments yet.",
    "policyPlaceholder": "Select policy",
    "branchCodePlaceholder": "Branch code",
    "warehousePlaceholder": "Select warehouse",
    "previewTitle": "Access Preview",
    "previewDescription": "Shows the effective scope resolution for the selected entity type.",
    "entityTypePlaceholder": "Select entity type",
    "previewEmpty": "Choose a user and entity type to see the effective scope here.",
    "previewUnrestricted": "Unrestricted access",
    "previewIncludeSelf": "Own records included",
    "previewAssignedOnly": "Assigned records only",
    "previewBranches": "Branches",
    "previewWarehouses": "Warehouses",
    "previewAssignments": "Matching Assignments",
    "noExplicitPolicy": "No explicit policy"
  }
}
